tree_math/__init__.py
tree_math/integration_test.py
tree_math/numpy.py
tree_math/_src/__init__.py
tree_math/_src/arg_util.py
tree_math/_src/func_wrappers.py
tree_math/_src/func_wrappers_test.py
tree_math/_src/numpy.py
tree_math/_src/numpy_test.py
tree_math/_src/structs.py
tree_math/_src/structs_test.py
tree_math/_src/test_util.py
tree_math/_src/vector.py
tree_math/_src/vector_test.py
tree_math-0.2.1.dist-info/LICENSE
tree_math-0.2.1.dist-info/METADATA
tree_math-0.2.1.dist-info/WHEEL
tree_math-0.2.1.dist-info/top_level.txt
tree_math-0.2.1.dist-info/RECORD
